{
  "kind": "collectionType",
  "collectionName": "contact_cards",
  "info": {
    "singularName": "contact-card",
    "pluralName": "contact-cards",
    "displayName": "5. Kontakty",
    "description": ""
  },
  "options": {
    "draftAndPublish": true
  },
  "pluginOptions": {},
  "attributes": {
    "name": {
      "type": "string",
      "required": true
    },
    "position": {
      "type": "string"
    },
    "email": {
      "type": "string"
    },
    "phone1": {
      "type": "string"
    },
    "phone2": {
      "type": "string"
    }
  }
}
